{
    "st-gallen": {
        "company": "Strongline SG",
        "query": "st-gallen",
        "contact": {
            "chief": "Herr Muster",
            "address": "Musterstrasse 33",
            "location": "St. Gallen, Schweiz"
        },
        "description": "Informationstext kommt hier hin",
        "shortDescription": "Kurzer Informationstext kommt hier hin"
    },
    "zuerich": {
        "company": "Strongline ZH",
        "query": "zurich",
        "contact": {
            "chief": "Herr Muster",
            "address": "Musterstrasse 33",
            "location": "Zürich, Schweiz"
        },
        "description": "Informationstext kommt hier hin",
        "shortDescription": "Kurzer Informationstext kommt hier hin"
    }
}
